cp4icl/__init__.py
cp4icl-0.0.1.dist-info/licenses/LICENSE
cp4icl-0.0.1.dist-info/METADATA
cp4icl-0.0.1.dist-info/WHEEL
cp4icl-0.0.1.dist-info/top_level.txt
cp4icl-0.0.1.dist-info/RECORD
