Metadata-Version: 2.4
Name: cp4icl
Version: 0.0.1
Summary: Conformal Prediction for In-Context Learning
Author: Maja Waldron
License: MIT
Requires-Python: >=3.9
License-File: LICENSE
Dynamic: license-file
